[
    {
        "name":"1"
        ,"items":[
            {
                "name":"1-1"
                ,"desc":"가나다"
            },
            {
                "name":"1-2"
                ,"desc":"test11"
            },
            {
                "name":"1-3"
                ,"desc":"test13"
            }
        ]
    }, {
        "name":"2"
        ,"items":[
            {
                "name":"2-1"
                ,"desc":"가나다"
            },
            {
                "name":"2-2"
                ,"desc":"test11"
            }
        ]
    }
]
